setup.py
apps/__init__.py
apps/text_processing.py
apps/topic_modelling.py
apps/covid_flu_classification/__init__.py
apps/covid_flu_classification/main.py
apps/few_show_text_classifier/__init__.py
apps/logistic_regression_image_classifier/__init__.py
apps/logistic_regression_image_classifier/main.py
apps/logistic_regression_image_classifier_with_pca/__init__.py
apps/logistic_regression_image_classifier_with_pca/main.py
apps/train_corrosion_model/__init__.py
apps/train_corrosion_model/eda_corrosion_images.py
apps/train_crack_model/__init__.py
apps/train_crack_model/train_crack_model.py
apps/train_crack_temp/__init__.py
apps/train_crack_temp/train_crack_model.py
mlutils/__init__.py
mlutils/config.py
mlutils/dataimporters/__init__.py
mlutils/dataimporters/mlutils_data_loader.py
mlutils/dataimporters/pytorch_data_importers/__init__.py
mlutils/dataimporters/pytorch_data_importers/pytorch_images_data_set_wrapper.py
mlutils/dataimporters/pytorch_data_importers/pytorch_task_sampler.py
mlutils/examples/__init__.py
mlutils/examples/eda_images.py
mlutils/examples/text_utils.py
mlutils/examples/train_classifier/__init__.py
mlutils/examples/train_classifier/train_corrosion_model.py
mlutils/featuresengine/__init__.py
mlutils/featuresengine/mlutils_feature_imputation.py
mlutils/featuresengine/mlutils_feature_transform.py
mlutils/model_test/__init__.py
mlutils/model_test/model_performance.py
mlutils/model_test/pytorch_model_tester.py
mlutils/models/__init__.py
mlutils/models/model_loaders.py
mlutils/models/models_enum.py
mlutils/models/pytorch_model_last_layer_adaptor.py
mlutils/models/classifiers/__init__.py
mlutils/models/classifiers/pytorch_classifiers/__init__.py
mlutils/models/classifiers/pytorch_classifiers/pytorch_few_shot_classifier.py
mlutils/models/classifiers/pytorch_classifiers/pytorch_prototypical_network_classifier.py
mlutils/models/classifiers/pytorch_classifiers/resnet_model_loader.py
mlutils/utils/__init__.py
mlutils/utils/array_utils.py
simplemlutils-0.0.3.dist-info/METADATA
simplemlutils-0.0.3.dist-info/WHEEL
simplemlutils-0.0.3.dist-info/RECORD
