Metadata-Version: 2.1
Name: simplemlutils
Version: 0.0.3
Summary: Easy to use utilities for ml modeling.
Project-URL: Homepage, https://github.com/pockerman/mlutils
Project-URL: Bug Tracker, https://github.com/pockerman/mlutils/issues
Author-email: Alexandros Giavaras <a.giavaras@gmail.com>
Classifier: License :: OSI Approved :: MIT License
Classifier: Operating System :: OS Independent
Classifier: Programming Language :: Python :: 3
Requires-Python: >=3.9
